{
  "associatedChampions": [],
  "associatedMaps": [],
  "blocks": [
    {
      "items": [
        {
          "count": 1,
          "id": "1055"
        },
        {
          "count": 1,
          "id": "2003"
        },
        {
          "count": 1,
          "id": "3340"
        }
      ],
      "type": "Most Frequent Starters (50% win - 22829 games)"
    },
    {
      "items": [
        {
          "count": 1,
          "id": "1036"
        },
        {
          "count": 3,
          "id": "2003"
        },
        {
          "count": 1,
          "id": "3340"
        }
      ],
      "type": "Highest Win Rate Starters (52% win - 438 games)"
    },
    {
      "items": [
        {
          "count": 1,
          "id": "3047"
        },
        {
          "count": 1,
          "id": "3071"
        },
        {
          "count": 1,
          "id": "3748"
        },
        {
          "count": 1,
          "id": "3053"
        },
        {
          "count": 1,
          "id": "3026"
        },
        {
          "count": 1,
          "id": "3065"
        }
      ],
      "type": "Most Frequent Build (44% win - 6562 games)"
    },
    {
      "items": [
        {
          "count": 1,
          "id": "3812"
        },
        {
          "count": 1,
          "id": "3047"
        },
        {
          "count": 1,
          "id": "3071"
        },
        {
          "count": 1,
          "id": "3026"
        },
        {
          "count": 1,
          "id": "3748"
        },
        {
          "count": 1,
          "id": "3194"
        }
      ],
      "type": "Highest Win Rate Build (49% win - 133 games)"
    },
    {
      "items": [
        {
          "count": 1,
          "id": "2003"
        },
        {
          "count": 1,
          "id": "2055"
        },
        {
          "count": 1,
          "id": "2031"
        },
        {
          "count": 1,
          "id": "2032"
        },
        {
          "count": 1,
          "id": "2033"
        },
        {
          "count": 1,
          "id": "2138"
        },
        {
          "count": 1,
          "id": "2139"
        },
        {
          "count": 1,
          "id": "2140"
        }
      ],
      "type": "Consumables QWE -> QWE (50% win - 17489 games)"
    },
    {
      "items": [
        {
          "count": 1,
          "id": "3340"
        },
        {
          "count": 1,
          "id": "3341"
        },
        {
          "count": 1,
          "id": "3364"
        },
        {
          "count": 1,
          "id": "3363"
        }
      ],
      "type": "QEEW -> QWE (54% win - 137 games)"
    }
  ],
  "champion": "Kled",
  "isGlobalForChampions": false,
  "isGlobalForMaps": true,
  "map": "any",
  "mode": "any",
  "priority": false,
  "sortrank": 1,
  "title": "Top 8.24",
  "type": "custom"
}