{
  "sortrank": 1,
  "type": "custom",
  "blocks": [
    {
      "items": [
        {
          "id": "1039",
          "count": 1
        },
        {
          "id": "2003",
          "count": 2
        },
        {
          "id": "3340",
          "count": 1
        },
        {
          "id": "3341",
          "count": 1
        },
        {
          "id": "3342",
          "count": 1
        }
      ],
      "type": "Most Frequent Starters (52.16% win - 1319 games)"
    },
    {
      "items": [
        {
          "id": "1039",
          "count": 1
        },
        {
          "id": "2003",
          "count": 2
        },
        {
          "id": "3340",
          "count": 1
        },
        {
          "id": "3341",
          "count": 1
        },
        {
          "id": "3342",
          "count": 1
        }
      ],
      "type": "Highest Win Rate Starters (52.16% win - 1319 games)"
    },
    {
      "items": [
        {
          "id": "3710",
          "count": 1
        },
        {
          "id": "3006",
          "count": 1
        },
        {
          "id": "3115",
          "count": 1
        },
        {
          "id": "3085",
          "count": 1
        },
        {
          "id": "3285",
          "count": 1
        },
        {
          "id": "3157",
          "count": 1
        }
      ],
      "type": "Most Frequent Build (53.62% win - 69 games)"
    },
    {
      "items": [
        {
          "id": "3710",
          "count": 1
        },
        {
          "id": "3115",
          "count": 1
        },
        {
          "id": "3006",
          "count": 1
        },
        {
          "id": "3085",
          "count": 1
        },
        {
          "id": "3285",
          "count": 1
        },
        {
          "id": "3100",
          "count": 1
        }
      ],
      "type": "Highest Win Rate Build (56.36% win - 32 games)"
    },
    {
      "items": [
        {
          "id": "2003",
          "count": 1
        },
        {
          "id": "2004",
          "count": 1
        },
        {
          "id": "2044",
          "count": 1
        },
        {
          "id": "2043",
          "count": 1
        },
        {
          "id": "2041",
          "count": 1
        },
        {
          "id": "2138",
          "count": 1
        },
        {
          "id": "2137",
          "count": 1
        },
        {
          "id": "2139",
          "count": 1
        },
        {
          "id": "2140",
          "count": 1
        }
      ],
      "type": "Consumables"
    },
    {
      "items": [
        {
          "id": "3361",
          "count": 1
        },
        {
          "id": "3362",
          "count": 1
        },
        {
          "id": "3364",
          "count": 1
        },
        {
          "id": "3363",
          "count": 1
        },
        {
          "id": "2003",
          "count": 1
        }
      ],
      "type": "EWQ -> EQW (56.32% win - 348 games)"
    },
    {
      "items": [
        {
          "id": "3361",
          "count": 1
        },
        {
          "id": "3362",
          "count": 1
        },
        {
          "id": "3364",
          "count": 1
        },
        {
          "id": "3363",
          "count": 1
        },
        {
          "id": "2003",
          "count": 1
        }
      ],
      "type": "EWQ -> EQW (56.32% win - 348 games)"
    }
  ],
  "title": "Jungle 5.5",
  "priority": false,
  "mode": "any",
  "isGlobalForMaps": true,
  "associatedChampions": [],
  "map": "any",
  "associatedMaps": [],
  "champion": "Kayle",
  "isGlobalForChampions": false
}