{
  "associatedChampions": [],
  "associatedMaps": [],
  "blocks": [
    {
      "items": [
        {
          "count": 1,
          "id": "1055"
        },
        {
          "count": 1,
          "id": "2003"
        },
        {
          "count": 1,
          "id": "3340"
        }
      ],
      "type": "Most Frequent Starters (49% win - 3684 games)"
    },
    {
      "items": [
        {
          "count": 1,
          "id": "1054"
        },
        {
          "count": 1,
          "id": "1055"
        },
        {
          "count": 1,
          "id": "2003"
        },
        {
          "count": 1,
          "id": "3340"
        }
      ],
      "type": "Highest Win Rate Starters (52% win - 174 games)"
    },
    {
      "items": [
        {
          "count": 1,
          "id": "3006"
        },
        {
          "count": 1,
          "id": "3031"
        },
        {
          "count": 1,
          "id": "3094"
        },
        {
          "count": 1,
          "id": "3087"
        },
        {
          "count": 1,
          "id": "3072"
        },
        {
          "count": 1,
          "id": "3026"
        }
      ],
      "type": "Most Frequent Build (36% win - 883 games)"
    },
    {
      "items": [
        {
          "count": 1,
          "id": "3031"
        },
        {
          "count": 1,
          "id": "3094"
        },
        {
          "count": 1,
          "id": "3006"
        },
        {
          "count": 1,
          "id": "3087"
        },
        {
          "count": 1,
          "id": "3072"
        },
        {
          "count": 1,
          "id": "3095"
        }
      ],
      "type": "Highest Win Rate Build (50% win - 125 games)"
    },
    {
      "items": [
        {
          "count": 1,
          "id": "2003"
        },
        {
          "count": 1,
          "id": "2055"
        },
        {
          "count": 1,
          "id": "2031"
        },
        {
          "count": 1,
          "id": "2032"
        },
        {
          "count": 1,
          "id": "2033"
        },
        {
          "count": 1,
          "id": "2138"
        },
        {
          "count": 1,
          "id": "2139"
        },
        {
          "count": 1,
          "id": "2140"
        }
      ],
      "type": "Consumables EWQ -> EQW (49% win - 3976 games)"
    },
    {
      "items": [
        {
          "count": 1,
          "id": "3340"
        },
        {
          "count": 1,
          "id": "3341"
        },
        {
          "count": 1,
          "id": "3364"
        },
        {
          "count": 1,
          "id": "3363"
        }
      ],
      "type": "EWQ -> EQW (49% win - 3976 games)"
    }
  ],
  "champion": "Tristana",
  "isGlobalForChampions": false,
  "isGlobalForMaps": true,
  "map": "any",
  "mode": "any",
  "priority": false,
  "sortrank": 1,
  "title": "ADC 9.23",
  "type": "custom"
}