{
  "type": "custom",
  "title": "Support 5.5",
  "mode": "any",
  "map": "any",
  "associatedMaps": [],
  "associatedChampions": [],
  "sortrank": 1,
  "isGlobalForChampions": false,
  "priority": false,
  "champion": "Nunu",
  "blocks": [
    {
      "type": "Most Frequent Starters (50.89% win - 112 games)",
      "items": [
        {
          "count": 1,
          "id": "2004"
        },
        {
          "count": 3,
          "id": "2003"
        },
        {
          "count": 1,
          "id": "3302"
        },
        {
          "count": 1,
          "id": "3340"
        },
        {
          "count": 1,
          "id": "3341"
        },
        {
          "count": 1,
          "id": "3342"
        }
      ]
    },
    {
      "type": "Highest Win Rate Starters (55.73% win - 61 games)",
      "items": [
        {
          "count": 2,
          "id": "2003"
        },
        {
          "count": 1,
          "id": "2004"
        },
        {
          "count": 1,
          "id": "3302"
        },
        {
          "count": 1,
          "id": "3340"
        },
        {
          "count": 1,
          "id": "3341"
        },
        {
          "count": 1,
          "id": "3342"
        }
      ]
    },
    {
      "type": "Most Frequent Build (45.28% win - 49 games)",
      "items": [
        {
          "count": 1,
          "id": "2049"
        },
        {
          "count": 1,
          "id": "3117"
        },
        {
          "count": 1,
          "id": "3401"
        },
        {
          "count": 1,
          "id": "3027"
        },
        {
          "count": 1,
          "id": "3110"
        },
        {
          "count": 1,
          "id": "3075"
        }
      ]
    },
    {
      "type": "Highest Win Rate Build (47.54% win - 47 games)",
      "items": [
        {
          "count": 1,
          "id": "2049"
        },
        {
          "count": 1,
          "id": "3401"
        },
        {
          "count": 1,
          "id": "3117"
        },
        {
          "count": 1,
          "id": "3110"
        },
        {
          "count": 1,
          "id": "3222"
        },
        {
          "count": 1,
          "id": "3143"
        }
      ]
    },
    {
      "type": "Consumables",
      "items": [
        {
          "count": 1,
          "id": "2003"
        },
        {
          "count": 1,
          "id": "2004"
        },
        {
          "count": 1,
          "id": "2044"
        },
        {
          "count": 1,
          "id": "2043"
        },
        {
          "count": 1,
          "id": "2041"
        },
        {
          "count": 1,
          "id": "2138"
        },
        {
          "count": 1,
          "id": "2137"
        },
        {
          "count": 1,
          "id": "2139"
        },
        {
          "count": 1,
          "id": "2140"
        }
      ]
    },
    {
      "type": "EWQ -> EWQ (43.47% win - 69 games)",
      "items": [
        {
          "count": 1,
          "id": "3361"
        },
        {
          "count": 1,
          "id": "3362"
        },
        {
          "count": 1,
          "id": "3364"
        },
        {
          "count": 1,
          "id": "3363"
        },
        {
          "count": 1,
          "id": "2003"
        }
      ]
    },
    {
      "type": "EQEW -> EWQ (53.84% win - 26 games)",
      "items": [
        {
          "count": 1,
          "id": "3361"
        },
        {
          "count": 1,
          "id": "3362"
        },
        {
          "count": 1,
          "id": "3364"
        },
        {
          "count": 1,
          "id": "3363"
        },
        {
          "count": 1,
          "id": "2003"
        }
      ]
    }
  ],
  "isGlobalForMpas": true
}