{
  "associatedChampions": [],
  "associatedMaps": [],
  "blocks": [
    {
      "items": [
        {
          "count": 1,
          "id": "2033"
        },
        {
          "count": 1,
          "id": "3340"
        }
      ],
      "type": "Most Frequent Starters (49% win - 3193 games)"
    },
    {
      "items": [
        {
          "count": 1,
          "id": "1054"
        },
        {
          "count": 1,
          "id": "2003"
        },
        {
          "count": 1,
          "id": "3340"
        }
      ],
      "type": "Highest Win Rate Starters (50% win - 402 games)"
    },
    {
      "items": [
        {
          "count": 1,
          "id": "3071"
        },
        {
          "count": 1,
          "id": "3047"
        },
        {
          "count": 1,
          "id": "3800"
        },
        {
          "count": 1,
          "id": "3065"
        },
        {
          "count": 1,
          "id": "3742"
        },
        {
          "count": 1,
          "id": "3193"
        }
      ],
      "type": "Most Frequent Build (38% win - 409 games)"
    },
    {
      "items": [
        {
          "count": 1,
          "id": "3071"
        },
        {
          "count": 1,
          "id": "3800"
        },
        {
          "count": 1,
          "id": "3047"
        },
        {
          "count": 1,
          "id": "3065"
        },
        {
          "count": 1,
          "id": "3075"
        },
        {
          "count": 1,
          "id": "3193"
        }
      ],
      "type": "Highest Win Rate Build (46% win - 162 games)"
    },
    {
      "items": [
        {
          "count": 1,
          "id": "2003"
        },
        {
          "count": 1,
          "id": "2055"
        },
        {
          "count": 1,
          "id": "2031"
        },
        {
          "count": 1,
          "id": "2032"
        },
        {
          "count": 1,
          "id": "2033"
        },
        {
          "count": 1,
          "id": "2138"
        },
        {
          "count": 1,
          "id": "2139"
        },
        {
          "count": 1,
          "id": "2140"
        }
      ],
      "type": "Consumables QEW -> QEW (50% win - 1436 games)"
    },
    {
      "items": [
        {
          "count": 1,
          "id": "3340"
        },
        {
          "count": 1,
          "id": "3341"
        },
        {
          "count": 1,
          "id": "3364"
        },
        {
          "count": 1,
          "id": "3363"
        }
      ],
      "type": "QEW -> QEW (66% win - 51 games)"
    }
  ],
  "champion": "Olaf",
  "isGlobalForChampions": false,
  "isGlobalForMaps": true,
  "map": "any",
  "mode": "any",
  "priority": false,
  "sortrank": 1,
  "title": "Top 7.22",
  "type": "custom"
}