{
  "associatedChampions": [],
  "associatedMaps": [],
  "blocks": [
    {
      "items": [
        {
          "count": 1,
          "id": "1055"
        },
        {
          "count": 1,
          "id": "2003"
        },
        {
          "count": 1,
          "id": "3340"
        }
      ],
      "type": "Most Frequent Starters (50% win - 39043 games)"
    },
    {
      "items": [
        {
          "count": 1,
          "id": "2031"
        },
        {
          "count": 1,
          "id": "3302"
        },
        {
          "count": 1,
          "id": "3340"
        }
      ],
      "type": "Highest Win Rate Starters (64% win - 87 games)"
    },
    {
      "items": [
        {
          "count": 1,
          "id": "3124"
        },
        {
          "count": 1,
          "id": "3006"
        },
        {
          "count": 1,
          "id": "3085"
        },
        {
          "count": 1,
          "id": "3153"
        },
        {
          "count": 1,
          "id": "3026"
        },
        {
          "count": 1,
          "id": "3036"
        }
      ],
      "type": "Most Frequent Build (46% win - 6440 games)"
    },
    {
      "items": [
        {
          "count": 1,
          "id": "3031"
        },
        {
          "count": 1,
          "id": "3085"
        },
        {
          "count": 1,
          "id": "3006"
        },
        {
          "count": 1,
          "id": "3087"
        },
        {
          "count": 1,
          "id": "3072"
        },
        {
          "count": 1,
          "id": "3153"
        }
      ],
      "type": "Highest Win Rate Build (59% win - 88 games)"
    },
    {
      "items": [
        {
          "count": 1,
          "id": "2003"
        },
        {
          "count": 1,
          "id": "2055"
        },
        {
          "count": 1,
          "id": "2031"
        },
        {
          "count": 1,
          "id": "2032"
        },
        {
          "count": 1,
          "id": "2033"
        },
        {
          "count": 1,
          "id": "2138"
        },
        {
          "count": 1,
          "id": "2139"
        },
        {
          "count": 1,
          "id": "2140"
        }
      ],
      "type": "Consumables EWQ -> EWQ (52% win - 15526 games)"
    },
    {
      "items": [
        {
          "count": 1,
          "id": "3340"
        },
        {
          "count": 1,
          "id": "3341"
        },
        {
          "count": 1,
          "id": "3364"
        },
        {
          "count": 1,
          "id": "3363"
        }
      ],
      "type": "QEW -> WEQ (66% win - 51 games)"
    }
  ],
  "champion": "Varus",
  "isGlobalForChampions": false,
  "isGlobalForMaps": true,
  "map": "any",
  "mode": "any",
  "priority": false,
  "sortrank": 1,
  "title": "ADC 7.22",
  "type": "custom"
}