{
  "associatedChampions": [],
  "associatedMaps": [],
  "blocks": [
    {
      "items": [
        {
          "count": 1,
          "id": "1054"
        },
        {
          "count": 1,
          "id": "2003"
        },
        {
          "count": 1,
          "id": "3340"
        }
      ],
      "type": "Most Frequent Starters (48% win - 1867 games)"
    },
    {
      "items": [
        {
          "count": 1,
          "id": "1029"
        },
        {
          "count": 4,
          "id": "2003"
        },
        {
          "count": 1,
          "id": "3340"
        }
      ],
      "type": "Highest Win Rate Starters (60% win - 85 games)"
    },
    {
      "items": [
        {
          "count": 1,
          "id": "3146"
        },
        {
          "count": 1,
          "id": "3020"
        },
        {
          "count": 1,
          "id": "3116"
        },
        {
          "count": 1,
          "id": "3151"
        },
        {
          "count": 1,
          "id": "3100"
        },
        {
          "count": 1,
          "id": "3800"
        }
      ],
      "type": "Most Frequent Build (39% win - 212 games)"
    },
    {
      "items": [
        {
          "count": 1,
          "id": "3151"
        },
        {
          "count": 1,
          "id": "3020"
        },
        {
          "count": 1,
          "id": "3135"
        },
        {
          "count": 1,
          "id": "3116"
        },
        {
          "count": 1,
          "id": "3089"
        },
        {
          "count": 1,
          "id": "3026"
        }
      ],
      "type": "Highest Win Rate Build (51% win - 52 games)"
    },
    {
      "items": [
        {
          "count": 1,
          "id": "2003"
        },
        {
          "count": 1,
          "id": "2055"
        },
        {
          "count": 1,
          "id": "2031"
        },
        {
          "count": 1,
          "id": "2032"
        },
        {
          "count": 1,
          "id": "2033"
        },
        {
          "count": 1,
          "id": "2138"
        },
        {
          "count": 1,
          "id": "2139"
        },
        {
          "count": 1,
          "id": "2140"
        }
      ],
      "type": "Consumables WQE -> WQE (53% win - 1028 games)"
    },
    {
      "items": [
        {
          "count": 1,
          "id": "3340"
        },
        {
          "count": 1,
          "id": "3341"
        },
        {
          "count": 1,
          "id": "3364"
        },
        {
          "count": 1,
          "id": "3363"
        }
      ],
      "type": "EQW -> WQE (57% win - 279 games)"
    }
  ],
  "champion": "Mordekaiser",
  "isGlobalForChampions": false,
  "isGlobalForMaps": true,
  "map": "any",
  "mode": "any",
  "priority": false,
  "sortrank": 1,
  "title": "Top 7.19",
  "type": "custom"
}