{
  "associatedChampions": [],
  "associatedMaps": [],
  "blocks": [
    {
      "items": [
        {
          "count": 2,
          "id": "2003"
        },
        {
          "count": 1,
          "id": "3303"
        },
        {
          "count": 1,
          "id": "3340"
        }
      ],
      "type": "Most Frequent Starters (52% win - 8204 games)"
    },
    {
      "items": [
        {
          "count": 2,
          "id": "2003"
        },
        {
          "count": 1,
          "id": "3303"
        },
        {
          "count": 1,
          "id": "3340"
        }
      ],
      "type": "Highest Win Rate Starters (52% win - 8204 games)"
    },
    {
      "items": [
        {
          "count": 1,
          "id": "3117"
        },
        {
          "count": 1,
          "id": "3504"
        },
        {
          "count": 1,
          "id": "3107"
        },
        {
          "count": 1,
          "id": "3092"
        },
        {
          "count": 1,
          "id": "3174"
        },
        {
          "count": 1,
          "id": "3190"
        }
      ],
      "type": "Most Frequent Build (45% win - 2094 games)"
    },
    {
      "items": [
        {
          "count": 1,
          "id": "3504"
        },
        {
          "count": 1,
          "id": "3117"
        },
        {
          "count": 1,
          "id": "3107"
        },
        {
          "count": 2,
          "id": "3092"
        },
        {
          "count": 1,
          "id": "3190"
        }
      ],
      "type": "Highest Win Rate Build (48% win - 892 games)"
    },
    {
      "items": [
        {
          "count": 1,
          "id": "2003"
        },
        {
          "count": 1,
          "id": "2055"
        },
        {
          "count": 1,
          "id": "2031"
        },
        {
          "count": 1,
          "id": "2032"
        },
        {
          "count": 1,
          "id": "2033"
        },
        {
          "count": 1,
          "id": "2138"
        },
        {
          "count": 1,
          "id": "2139"
        },
        {
          "count": 1,
          "id": "2140"
        }
      ],
      "type": "Consumables WEQ -> WEQ (54% win - 2260 games)"
    },
    {
      "items": [
        {
          "count": 1,
          "id": "3340"
        },
        {
          "count": 1,
          "id": "3341"
        },
        {
          "count": 1,
          "id": "3364"
        },
        {
          "count": 1,
          "id": "3363"
        }
      ],
      "type": "WQWE -> WEQ (66% win - 128 games)"
    }
  ],
  "champion": "Janna",
  "isGlobalForChampions": false,
  "isGlobalForMaps": true,
  "map": "any",
  "mode": "any",
  "priority": false,
  "sortrank": 1,
  "title": "Support 9.18",
  "type": "custom"
}