{
  "associatedChampions": [],
  "associatedMaps": [],
  "blocks": [
    {
      "items": [
        {
          "count": 1,
          "id": "1039"
        },
        {
          "count": 1,
          "id": "2031"
        },
        {
          "count": 1,
          "id": "3340"
        }
      ],
      "type": "Most Frequent Starters (48% win - 9022 games)"
    },
    {
      "items": [
        {
          "count": 1,
          "id": "1041"
        },
        {
          "count": 1,
          "id": "2031"
        },
        {
          "count": 1,
          "id": "3340"
        }
      ],
      "type": "Highest Win Rate Starters (53% win - 4233 games)"
    },
    {
      "items": [
        {
          "count": 1,
          "id": "1414"
        },
        {
          "count": 1,
          "id": "3158"
        },
        {
          "count": 1,
          "id": "3100"
        },
        {
          "count": 1,
          "id": "3157"
        },
        {
          "count": 1,
          "id": "3135"
        },
        {
          "count": 1,
          "id": "3089"
        }
      ],
      "type": "Most Frequent Build (36% win - 2094 games)"
    },
    {
      "items": [
        {
          "count": 1,
          "id": "1414"
        },
        {
          "count": 1,
          "id": "3100"
        },
        {
          "count": 1,
          "id": "3158"
        },
        {
          "count": 1,
          "id": "3174"
        },
        {
          "count": 1,
          "id": "3157"
        },
        {
          "count": 1,
          "id": "3089"
        }
      ],
      "type": "Highest Win Rate Build (41% win - 978 games)"
    },
    {
      "items": [
        {
          "count": 1,
          "id": "2003"
        },
        {
          "count": 1,
          "id": "2055"
        },
        {
          "count": 1,
          "id": "2031"
        },
        {
          "count": 1,
          "id": "2032"
        },
        {
          "count": 1,
          "id": "2033"
        },
        {
          "count": 1,
          "id": "2138"
        },
        {
          "count": 1,
          "id": "2139"
        },
        {
          "count": 1,
          "id": "2140"
        }
      ],
      "type": "Consumables QWE -> QEW (50% win - 10913 games)"
    },
    {
      "items": [
        {
          "count": 1,
          "id": "3340"
        },
        {
          "count": 1,
          "id": "3341"
        },
        {
          "count": 1,
          "id": "3364"
        },
        {
          "count": 1,
          "id": "3363"
        }
      ],
      "type": "QWE -> QEW (61% win - 189 games)"
    }
  ],
  "champion": "Nidalee",
  "isGlobalForChampions": false,
  "isGlobalForMaps": true,
  "map": "any",
  "mode": "any",
  "priority": false,
  "sortrank": 1,
  "title": "Jungle 7.23",
  "type": "custom"
}