{
  "associatedChampions": [],
  "associatedMaps": [],
  "blocks": [
    {
      "items": [
        {
          "count": 1,
          "id": "1039"
        },
        {
          "count": 1,
          "id": "2031"
        },
        {
          "count": 1,
          "id": "3340"
        }
      ],
      "type": "Most Frequent Starters (50% win - 20980 games)"
    },
    {
      "items": [
        {
          "count": 1,
          "id": "1006"
        },
        {
          "count": 1,
          "id": "1039"
        },
        {
          "count": 1,
          "id": "3340"
        }
      ],
      "type": "Highest Win Rate Starters (65% win - 26 games)"
    },
    {
      "items": [
        {
          "count": 1,
          "id": "1401"
        },
        {
          "count": 1,
          "id": "3047"
        },
        {
          "count": 1,
          "id": "3078"
        },
        {
          "count": 1,
          "id": "3742"
        },
        {
          "count": 1,
          "id": "3065"
        },
        {
          "count": 1,
          "id": "3053"
        }
      ],
      "type": "Most Frequent Build (39% win - 2253 games)"
    },
    {
      "items": [
        {
          "count": 1,
          "id": "3078"
        },
        {
          "count": 1,
          "id": "3009"
        },
        {
          "count": 1,
          "id": "1401"
        },
        {
          "count": 1,
          "id": "3142"
        },
        {
          "count": 1,
          "id": "3742"
        },
        {
          "count": 1,
          "id": "3053"
        }
      ],
      "type": "Highest Win Rate Build (48% win - 704 games)"
    },
    {
      "items": [
        {
          "count": 1,
          "id": "2003"
        },
        {
          "count": 1,
          "id": "2055"
        },
        {
          "count": 1,
          "id": "2031"
        },
        {
          "count": 1,
          "id": "2032"
        },
        {
          "count": 1,
          "id": "2033"
        },
        {
          "count": 1,
          "id": "2138"
        },
        {
          "count": 1,
          "id": "2139"
        },
        {
          "count": 1,
          "id": "2140"
        }
      ],
      "type": "Consumables QWE -> QEW (51% win - 30377 games)"
    },
    {
      "items": [
        {
          "count": 1,
          "id": "3340"
        },
        {
          "count": 1,
          "id": "3341"
        },
        {
          "count": 1,
          "id": "3364"
        },
        {
          "count": 1,
          "id": "3363"
        }
      ],
      "type": "QEEQ -> EQW (62% win - 51 games)"
    }
  ],
  "champion": "Hecarim",
  "isGlobalForChampions": false,
  "isGlobalForMaps": true,
  "map": "any",
  "mode": "any",
  "priority": false,
  "sortrank": 1,
  "title": "Jungle 7.22",
  "type": "custom"
}